olinda/__init__.py
olinda/cli/__init__.py
olinda/cli/main.py
olinda/configs/base.gin
olinda/data/__init__.py
olinda/data/featurized_smiles.py
olinda/data/generic_model_output.py
olinda/data/reference_smiles.py
olinda/distillation.py
olinda/featurizer.py
olinda/flat2grid.joblib
olinda/generic_model.py
olinda/models/__init__.py
olinda/models/base.py
olinda/models/olinda_zero.py
olinda/pipelines/__init__.py
olinda/utils.py
olinda-0.1.0.dist-info/entry_points.txt
olinda-0.1.0.dist-info/WHEEL
olinda-0.1.0.dist-info/METADATA
olinda-0.1.0.dist-info/RECORD
